Workbook

Sheet CONFIGURACION
A1: PAINT PRINT -- CONFIGURACION DEL SISTEMA
A2: Modifica solo los valores en columna B. Todo el sistema se actualiza automaticamente.
A4: PARAMETRO | B4: VALOR | C4: DESCRIPCION
A5: Valor hora de trabajo $ | B5: 4000 | C5: CLP por hora. Cambia aqui y todos los costos se actualizan.
A6: Margen minimo % | B6: 0.3 | C6: 30% -- Precio mas bajo posible. Por debajo de este precio pierdes.
A7: Margen recomendado % | B7: 0.55 | C7: 55% -- Precio justo. Cubre todo y genera utilidad real.
A8: Margen ideal % | B8: 0.7 | C8: 70% -- Precio premium. Para productos de alta demanda o exclusivos.
A9: Gastos fijos % sobre costo | B9: 0.15 | C9: 15% -- Electricidad, desgaste maquinas, internet, etc.
A10: Moneda | B10: CLP | C10: Peso chileno. Todos los precios y costos en CLP.
A12: LISTAS DE REFERENCIA -- uso interno del sistema (no borrar)
A13: UNIDAD_COMPRA | B13: UNIDAD_CONSUMO | C13: CATEGORIA | D13: ESTADO_PEDIDO | E13: TIPO_MOV | F13: CANAL_VENTA | G13: UNIDAD_VENTA
A14: pack | B14: unidad | C14: Papel y cartulina | D14: Cotizado | E14: ENTRADA | F14: Instagram | G14: pieza
A15: metro | B15: hoja | C15: Vinil | D15: Aprobado | E15: SALIDA | F15: WhatsApp | G15: set 10u
A16: litro | B16: metro | C16: Tinta e insumos | D16: En produccion | E16: MERMA | F16: Referido | G16: set 20u
A17: rollo | B17: centimetro | C17: Adhesivos | D17: Entregado | E17: AJUSTE | F17: Directo | G17: set 50u
A18: frasco | B18: cm2 | C18: Gran formato | D18: Pagado | F18: Feria | G18: set 100u
A19: caja | B19: ml | C19: Textil | D19: Archivado | F19: TikTok | G19: metro
A20: unidad | B20: gramo | C20: Madera y plastico | F20: Otro | G20: par
A21: hoja | B21: uso | C21: Otros | G21: Kit
A22: set | B22: rollo
A23: saco
A24: resma

Sheet MATERIALES
A1: PAINT PRINT -- CONTROL DE MATERIALES E INVENTARIO
A2: AZUL = Ingresa tu | VERDE = Calculado automatico | Actualiza D y H cada vez que compres materiales
A3: EQUIV. CONSUMO = cuantas unidades de consumo trae cada unidad de compra (ej: 1 pack = 20 hojas -> 20)
A4: ID | B4: MATERIAL | C4: CATEGORIA | D4: UNID. COMPRA | E4: EQUIV. CONSUMO | F4: UNID. CONSUMO | G4: CANT. COMPRADA | H4: COSTO TOTAL $ | I4: COSTO / UNID $ | J4: STOCK INICIAL | K4: ENTRADAS | L4: SALIDAS | M4: STOCK ACTUAL | N4: STOCK MINIMO | AO4: ALERTA | AP4: VALOR INV $ | AQ4: PROVEEDOR | AR4: FECHA COMPRA
A5: MP-001 | B5: Papel fotografico 260g | C5: Papel y cartulina | D5: pack | E5: 20 | F5: hoja | G5: 1 | H5: 5000 | I5: =IFERROR(H5/(G5*E5),0) -> 250 | J5: 100 | K5: =IFERROR(SUMIFS(MOVIMIENTOS!$E:$E,MOVIMIENTOS!$C:$C,$A5,MOVIMIENTOS!$B:$B,"ENTRADA"),0) -> 100 | L5: =IFERROR(SUMIFS(MOVIMIENTOS!$E:$E,MOVIMIENTOS!$C:$C,$A5,MOVIMIENTOS!$B:$B,"SALIDA")+SUMIFS(MOVIMIENTOS!$E:$E,MOVIMIENTOS!$C:$C,$A5,MOVIMIENTOS!$B:$B,"MERMA"),0) -> 0 | M5: =IFERROR(J5+K5-L5,0) -> 200 | N5: 20 | O5: =IF(M5<=N5,"REPONER","OK") -> OK | P5: =IFERROR(M5*I5,0) -> 50000 | AO5: =IF(M5<=N5,"REPONER","OK") -> OK | AP5: =IFERROR(M5*I5,0) -> 50000 | AQ5: Papeleria Central | AR5: 46195
A6: MP-002 | B6: Papel fotografico 180g | C6: Papel y cartulina | D6: pack | E6: 50 | F6: hoja | G6: 1 | H6: 3500 | I6: =IFERROR(H6/(G6*E6),0) -> 70 | J6: 100 | K6: =IFERROR(SUMIFS(MOVIMIENTOS!$E:$E,MOVIMIENTOS!$C:$C,$A6,MOVIMIENTOS!$B:$B,"ENTRADA"),0) -> 100 | L6: =IFERROR(SUMIFS(MOVIMIENTOS!$E:$E,MOVIMIENTOS!$C:$C,$A6,MOVIMIENTOS!$B:$B,"SALIDA")+SUMIFS(MOVIMIENTOS!$E:$E,MOVIMIENTOS!$C:$C,$A6,MOVIMIENTOS!$B:$B,"MERMA"),0) -> 0 | M6: =IFERROR(J6+K6-L6,0) -> 200 | N6: 20 | O6: =IF(M6<=N6,"REPONER","OK") -> OK | P6: =IFERROR(M6*I6,0) -> 14000 | AO6: =IF(M6<=N6,"REPONER","OK") -> OK | AP6: =IFERROR(M6*I6,0) -> 14000 | AQ6: Papeleria Central | AR6: 46195
A7: MP-003 | B7: Vinil imprimible (pack 20u) | C7: Vinil | D7: pack | E7: 20 | F7: unidad | G7: 1 | H7: 8000 | I7: =IFERROR(H7/(G7*E7),0) -> 400 | J7: 40 | K7: =IFERROR(SUMIFS(MOVIMIENTOS!$E:$E,MOVIMIENTOS!$C:$C,$A7,MOVIMIENTOS!$B:$B,"ENTRADA"),0) -> 40 | L7: =IFERROR(SUMIFS(MOVIMIENTOS!$E:$E,MOVIMIENTOS!$C:$C,$A7,MOVIMIENTOS!$B:$B,"SALIDA")+SUMIFS(MOVIMIENTOS!$E:$E,MOVIMIENTOS!$C:$C,$A7,MOVIMIENTOS!$B:$B,"MERMA"),0) -> 0 | M7: =IFERROR(J7+K7-L7,0) -> 80 | N7: 10 | O7: =IF(M7<=N7,"REPONER","OK") -> OK | P7: =IFERROR(M7*I7,0) -> 32000 | AO7: =IF(M7<=N7,"REPONER","OK") -> OK | AP7: =IFERROR(M7*I7,0) -> 32000 | AQ7: Insumos Graficos | AR7: 46195
A8: MP-004 | B8: Vinil textil por metro | C8: Textil | D8: metro | E8: 100 | F8: centimetro | G8: 2 | H8: 12000 | I8: =IFERROR(H8/(G8*E8),0) -> 60 | J8: 500 | K8: =IFERROR(SUMIFS(MOVIMIENTOS!$E:$E,MOVIMIENTOS!$C:$C,$A8,MOVIMIENTOS!$B:$B,"ENTRADA"),0) -> 500 | L8: =IFERROR(SUMIFS(MOVIMIENTOS!$E:$E,MOVIMIENTOS!$C:$C,$A8,MOVIMIENTOS!$B:$B,"SALIDA")+SUMIFS(MOVIMIENTOS!$E:$E,MOVIMIENTOS!$C:$C,$A8,MOVIMIENTOS!$B:$B,"MERMA"),0) -> 0 | M8: =IFERROR(J8+K8-L8,0) -> 1000 | N8: 200 | O8: =IF(M8<=N8,"REPONER","OK") -> OK | P8: =IFERROR(M8*I8,0) -> 60000 | AO8: =IF(M8<=N8,"REPONER","OK") -> OK | AP8: =IFERROR(M8*I8,0) -> 60000 | AQ8: Textiles Graficos | AR8: 46195
A9: MP-005 | B9: Papel adhesivo | C9: Papel y cartulina | D9: pack | E9: 25 | F9: hoja | G9: 1 | H9: 4500 | I9: =IFERROR(H9/(G9*E9),0) -> 180 | J9: 50 | K9: =IFERROR(SUMIFS(MOVIMIENTOS!$E:$E,MOVIMIENTOS!$C:$C,$A9,MOVIMIENTOS!$B:$B,"ENTRADA"),0) -> 50 | L9: =IFERROR(SUMIFS(MOVIMIENTOS!$E:$E,MOVIMIENTOS!$C:$C,$A9,MOVIMIENTOS!$B:$B,"SALIDA")+SUMIFS(MOVIMIENTOS!$E:$E,MOVIMIENTOS!$C:$C,$A9,MOVIMIENTOS!$B:$B,"MERMA"),0) -> 0 | M9: =IFERROR(J9+K9-L9,0) -> 100 | N9: 10 | O9: =IF(M9<=N9,"REPONER","OK") -> OK | P9: =IFERROR(M9*I9,0) -> 18000 | AO9: =IF(M9<=N9,"REPONER","OK") -> OK | AP9: =IFERROR(M9*I9,0) -> 18000 | AQ9: Papeleria Central | AR9: 46195
A10: MP-006 | B10: Cartulina opalina | C10: Papel y cartulina | D10: pack | E10: 20 | F10: hoja | G10: 1 | H10: 3000 | I10: =IFERROR(H10/(G10*E10),0) -> 150 | J10: 40 | K10: =IFERROR(SUMIFS(MOVIMIENTOS!$E:$E,MOVIMIENTOS!$C:$C,$A10,MOVIMIENTOS!$B:$B,"ENTRADA"),0) -> 40 | L10: =IFERROR(SUMIFS(MOVIMIENTOS!$E:$E,MOVIMIENTOS!$C:$C,$A10,MOVIMIENTOS!$B:$B,"SALIDA")+SUMIFS(MOVIMIENTOS!$E:$E,MOVIMIENTOS!$C:$C,$A10,MOVIMIENTOS!$B:$B,"MERMA"),0) -> 0 | M10: =IFERROR(J10+K10-L10,0) -> 80 | N10: 10 | O10: =IF(M10<=N10,"REPONER","OK") -> OK | P10: =IFERROR(M10*I10,0) -> 12000 | AO10: =IF(M10<=N10,"REPONER","OK") -> OK | AP10: =IFERROR(M10*I10,0) -> 12000 | AQ10: Papeleria Central | AR10: 46195
A11: MP-007 | B11: Pegamento | C11: Adhesivos | D11: frasco | E11: 50 | F11: uso | G11: 1 | H11: 2500 | I11: =IFERROR(H11/(G11*E11),0) -> 50 | J11: 3 | K11: =IFERROR(SUMIFS(MOVIMIENTOS!$E:$E,MOVIMIENTOS!$C:$C,$A11,MOVIMIENTOS!$B:$B,"ENTRADA"),0) -> 3 | L11: =IFERROR(SUMIFS(MOVIMIENTOS!$E:$E,MOVIMIENTOS!$C:$C,$A11,MOVIMIENTOS!$B:$B,"SALIDA")+SUMIFS(MOVIMIENTOS!$E:$E,MOVIMIENTOS!$C:$C,$A11,MOVIMIENTOS!$B:$B,"MERMA"),0) -> 0 | M11: =IFERROR(J11+K11-L11,0) -> 6 | N11: 1 | O11: =IF(M11<=N11,"REPONER","OK") -> OK | P11: =IFERROR(M11*I11,0) -> 300 | AO11: =IF(M11<=N11,"REPONER","OK") -> OK | AP11: =IFERROR(M11*I11,0) -> 300 | AQ11: Ferreteria Local | AR11: 46195
A12: MP-008 | B12: Palitos para toppers | C12: Otros | D12: pack | E12: 100 | F12: unidad | G12: 1 | H12: 1500 | I12: =IFERROR(H12/(G12*E12),0) -> 15 | J12: 200 | K12: =IFERROR(SUMIFS(MOVIMIENTOS!$E:$E,MOVIMIENTOS!$C:$C,$A12,MOVIMIENTOS!$B:$B,"ENTRADA"),0) -> 200 | L12: =IFERROR(SUMIFS(MOVIMIENTOS!$E:$E,MOVIMIENTOS!$C:$C,$A12,MOVIMIENTOS!$B:$B,"SALIDA")+SUMIFS(MOVIMIENTOS!$E:$E,MOVIMIENTOS!$C:$C,$A12,MOVIMIENTOS!$B:$B,"MERMA"),0) -> 0 | M12: =IFERROR(J12+K12-L12,0) -> 400 | N12: 50 | O12: =IF(M12<=N12,"REPONER","OK") -> OK | P12: =IFERROR(M12*I12,0) -> 6000 | AO12: =IF(M12<=N12,"REPONER","OK") -> OK | AP12: =IFERROR(M12*I12,0) -> 6000 | AQ12: Cotillon Center | AR12: 46195
A13: MP-009 | B13: Tinta Epson (set completo) | C13: Tinta e insumos | D13: set | E13: 200 | F13: uso | G13: 1 | H13: 35000 | I13: =IFERROR(H13/(G13*E13),0) -> 175 | J13: 400 | K13: =IFERROR(SUMIFS(MOVIMIENTOS!$E:$E,MOVIMIENTOS!$C:$C,$A13,MOVIMIENTOS!$B:$B,"ENTRADA"),0) -> 400 | L13: =IFERROR(SUMIFS(MOVIMIENTOS!$E:$E,MOVIMIENTOS!$C:$C,$A13,MOVIMIENTOS!$B:$B,"SALIDA")+SUMIFS(MOVIMIENTOS!$E:$E,MOVIMIENTOS!$C:$C,$A13,MOVIMIENTOS!$B:$B,"MERMA"),0) -> 0 | M13: =IFERROR(J13+K13-L13,0) -> 800 | N13: 100 | O13: =IF(M13<=N13,"REPONER","OK") -> OK | P13: =IFERROR(M13*I13,0) -> 140000 | AO13: =IF(M13<=N13,"REPONER","OK") -> OK | AP13: =IFERROR(M13*I13,0) -> 140000 | AQ13: Epson Chile | AR13: 46195
A14: MP-010 | B14: Lona para pendones | C14: Gran formato | D14: rollo | E14: 50000 | F14: cm2 | G14: 1 | H14: 40000 | I14: =IFERROR(H14/(G14*E14),0) -> 0.8 | J14: 50000 | K14: =IFERROR(SUMIFS(MOVIMIENTOS!$E:$E,MOVIMIENTOS!$C:$C,$A14,MOVIMIENTOS!$B:$B,"ENTRADA"),0) -> 50000 | L14: =IFERROR(SUMIFS(MOVIMIENTOS!$E:$E,MOVIMIENTOS!$C:$C,$A14,MOVIMIENTOS!$B:$B,"SALIDA")+SUMIFS(MOVIMIENTOS!$E:$E,MOVIMIENTOS!$C:$C,$A14,MOVIMIENTOS!$B:$B,"MERMA"),0) -> 0 | M14: =IFERROR(J14+K14-L14,0) -> 100000 | N14: 10000 | O14: =IF(M14<=N14,"REPONER","OK") -> OK | P14: =IFERROR(M14*I14,0) -> 80000 | AO14: =IF(M14<=N14,"REPONER","OK") -> OK | AP14: =IFERROR(M14*I14,0) -> 80000 | AQ14: Imprenta Mayorista | AR14: 46195

Sheet RECETAS
A1: PAINT PRINT -- RECETAS DE PRODUCTOS
A2: Selecciona producto y material desde las listas. Ingresa solo la CANTIDAD USADA. El costo se calcula automaticamente.
A3: El nombre del producto en columna B debe existir exactamente igual en la hoja PRODUCTOS.
A4: ID RECETA | B4: PRODUCTO | C4: ID MATERIAL | D4: MATERIAL | E4: UNID. CONSUMO | F4: COSTO / UNID $ | G4: CANT. USADA | H4: SUBTOTAL $ | I4: NOTA
A5: R-TOP-01 | B5: Topper personalizado | C5: MP-001 | D5: =IFERROR(VLOOKUP(C5,MATERIALES!$A:$B,2,0),"") -> Papel fotografico 260g | E5: =IFERROR(VLOOKUP(C5,MATERIALES!$A:$F,6,0),"") -> hoja | F5: =IFERROR(VLOOKUP(C5,MATERIALES!$A:$I,9,0),0) -> 250 | G5: 0.5 | H5: =IFERROR(G5*F5,0) -> 125 | I5: Media hoja 260g por topper
A6: R-TOP-02 | B6: Topper personalizado | C6: MP-007 | D6: =IFERROR(VLOOKUP(C6,MATERIALES!$A:$B,2,0),"") -> Pegamento | E6: =IFERROR(VLOOKUP(C6,MATERIALES!$A:$F,6,0),"") -> uso | F6: =IFERROR(VLOOKUP(C6,MATERIALES!$A:$I,9,0),0) -> 50 | G6: 0.1 | H6: =IFERROR(G6*F6,0) -> 5 | I6: Pegamento para base
A7: R-TOP-03 | B7: Topper personalizado | C7: MP-008 | D7: =IFERROR(VLOOKUP(C7,MATERIALES!$A:$B,2,0),"") -> Palitos para toppers | E7: =IFERROR(VLOOKUP(C7,MATERIALES!$A:$F,6,0),"") -> unidad | F7: =IFERROR(VLOOKUP(C7,MATERIALES!$A:$I,9,0),0) -> 15 | G7: 2 | H7: =IFERROR(G7*F7,0) -> 30 | I7: 2 palitos por topper
A8: R-TOP-04 | B8: Topper personalizado | C8: MP-009 | D8: =IFERROR(VLOOKUP(C8,MATERIALES!$A:$B,2,0),"") -> Tinta Epson (set completo) | E8: =IFERROR(VLOOKUP(C8,MATERIALES!$A:$F,6,0),"") -> uso | F8: =IFERROR(VLOOKUP(C8,MATERIALES!$A:$I,9,0),0) -> 175 | G8: 0.3 | H8: =IFERROR(G8*F8,0) -> 52.5 | I8: Impresion color completa
A9: R-TAR-01 | B9: Tarjetas presentacion | C9: MP-002 | D9: =IFERROR(VLOOKUP(C9,MATERIALES!$A:$B,2,0),"") -> Papel fotografico 180g | E9: =IFERROR(VLOOKUP(C9,MATERIALES!$A:$F,6,0),"") -> hoja | F9: =IFERROR(VLOOKUP(C9,MATERIALES!$A:$I,9,0),0) -> 70 | G9: 9 | H9: =IFERROR(G9*F9,0) -> 630 | I9: 9 hojas para 100 tarjetas
A10: R-TAR-02 | B10: Tarjetas presentacion | C10: MP-009 | D10: =IFERROR(VLOOKUP(C10,MATERIALES!$A:$B,2,0),"") -> Tinta Epson (set completo) | E10: =IFERROR(VLOOKUP(C10,MATERIALES!$A:$F,6,0),"") -> uso | F10: =IFERROR(VLOOKUP(C10,MATERIALES!$A:$I,9,0),0) -> 175 | G10: 0.5 | H10: =IFERROR(G10*F10,0) -> 87.5 | I10: Impresion doble cara
A11: R-POL-01 | B11: Polera sublimada | C11: MP-004 | D11: =IFERROR(VLOOKUP(C11,MATERIALES!$A:$B,2,0),"") -> Vinil textil por metro | E11: =IFERROR(VLOOKUP(C11,MATERIALES!$A:$F,6,0),"") -> centimetro | F11: =IFERROR(VLOOKUP(C11,MATERIALES!$A:$I,9,0),0) -> 60 | G11: 60 | H11: =IFERROR(G11*F11,0) -> 3600 | I11: 60 cm vinil textil por polera
A12: R-POL-02 | B12: Polera sublimada | C12: MP-009 | D12: =IFERROR(VLOOKUP(C12,MATERIALES!$A:$B,2,0),"") -> Tinta Epson (set completo) | E12: =IFERROR(VLOOKUP(C12,MATERIALES!$A:$F,6,0),"") -> uso | F12: =IFERROR(VLOOKUP(C12,MATERIALES!$A:$I,9,0),0) -> 175 | G12: 0.2 | H12: =IFERROR(G12*F12,0) -> 35 | I12: Impresion transfer
A13: R-STI-01 | B13: Sticker personalizado | C13: MP-003 | D13: =IFERROR(VLOOKUP(C13,MATERIALES!$A:$B,2,0),"") -> Vinil imprimible (pack 20u) | E13: =IFERROR(VLOOKUP(C13,MATERIALES!$A:$F,6,0),"") -> unidad | F13: =IFERROR(VLOOKUP(C13,MATERIALES!$A:$I,9,0),0) -> 400 | G13: 1 | H13: =IFERROR(G13*F13,0) -> 400 | I13: 1 lamina vinil por set 20u
A14: R-STI-02 | B14: Sticker personalizado | C14: MP-009 | D14: =IFERROR(VLOOKUP(C14,MATERIALES!$A:$B,2,0),"") -> Tinta Epson (set completo) | E14: =IFERROR(VLOOKUP(C14,MATERIALES!$A:$F,6,0),"") -> uso | F14: =IFERROR(VLOOKUP(C14,MATERIALES!$A:$I,9,0),0) -> 175 | G14: 0.2 | H14: =IFERROR(G14*F14,0) -> 35 | I14: Impresion a color
A15: R-PEN-01 | B15: Pendon publicitario | C15: MP-010 | D15: =IFERROR(VLOOKUP(C15,MATERIALES!$A:$B,2,0),"") -> Lona para pendones | E15: =IFERROR(VLOOKUP(C15,MATERIALES!$A:$F,6,0),"") -> cm2 | F15: =IFERROR(VLOOKUP(C15,MATERIALES!$A:$I,9,0),0) -> 0.8 | G15: 9600 | H15: =IFERROR(G15*F15,0) -> 7680 | I15: 9600 cm2 por pendon 60x160
A16: R-PEN-02 | B16: Pendon publicitario | C16: MP-009 | D16: =IFERROR(VLOOKUP(C16,MATERIALES!$A:$B,2,0),"") -> Tinta Epson (set completo) | E16: =IFERROR(VLOOKUP(C16,MATERIALES!$A:$F,6,0),"") -> uso | F16: =IFERROR(VLOOKUP(C16,MATERIALES!$A:$I,9,0),0) -> 175 | G16: 0.5 | H16: =IFERROR(G16*F16,0) -> 87.5 | I16: Impresion gran formato
... A25: R-VIN-02 | B25: Vinil personalizado | C25: MP-009 | D25: =IFERROR(VLOOKUP(C25,MATERIALES!$A:$B,2,0),"") -> Tinta Epson (set completo) | E25: =IFERROR(VLOOKUP(C25,MATERIALES!$A:$F,6,0),"") -> uso | F25: =IFERROR(VLOOKUP(C25,MATERIALES!$A:$I,9,0),0) -> 175 | G25: 0.15 | H25: =IFERROR(G25*F25,0) -> 26.25 | I25: Impresion vinil

Sheet PRODUCTOS
A1: PAINT PRINT -- CATALOGO Y COSTOS DE PRODUCTOS
A2: El costo de materiales viene automaticamente de RECETAS. Ingresa solo los TIEMPOS y el PRECIO ACTUAL.
A3: PRECIO MINIMO(30%) / PRECIO JUSTO(55%) / PRECIO IDEAL(70%) se calculan desde CONFIGURACION automaticamente.
A4: CODIGO | B4: PRODUCTO | C4: DESCRIPCION | D4: UNID. VENTA | E4: COSTO MAT $ | F4: MIN DIS | G4: MIN IMP | H4: MIN COR | I4: MIN ARM | J4: MIN TOTAL | K4: $/HORA | L4: COSTO MO $ | M4: % GF | N4: GASTOS FIJ $ | AO4: COSTO TOTAL $ | AP4: PRECIO MIN $ | AQ4: PRECIO JUSTO $ | AR4: PRECIO IDEAL $ | AS4: PRECIO ACTUAL $ | AT4: MARGEN ACT % | AU4: ESTADO
A5: PP-001 | B5: Topper personalizado | C5: Toppers para eventos y fiestas | D5: pieza | E5: =IFERROR(SUMIF(RECETAS!$B:$B,B5,RECETAS!$H:$H),0) -> 212.5 | F5: 5 | G5: 5 | H5: 0 | I5: 5 | J5: =F5+G5+H5+I5 -> 15 | K5: =IFERROR(CONFIGURACION!$B$5,0) -> 4000 | L5: =IFERROR(J5*K5/60,0) -> 1000 | M5: =IFERROR(CONFIGURACION!$B$9,0) -> 0.15 | N5: =IFERROR((E5+L5)*M5,0) -> 181.875 | O5: =IFERROR(E5+L5+N5,0) -> 1394.375 | P5: =IFERROR(ROUNDUP(O5/(1-CONFIGURACION!$B$6),0),0) -> 1992 | Q5: =IFERROR(ROUNDUP(O5/(1-CONFIGURACION!$B$7),0),0) -> 3099 | R5: =IFERROR(ROUNDUP(O5/(1-CONFIGURACION!$B$8),0),0) -> 4648 | S5: 6500 | T5: =IF(S5>0,(S5-O5)/S5,0) -> 0.78548077 | U5: =IF(S5=0,"SIN PRECIO",IF(T5<CONFIGURACION!$B$6,"BAJO COSTO",IF(T5<CONFIGURACION!$B$7,"REVISAR","OK"))) -> OK | AO5: =IFERROR(E5+L5+N5,0) -> 1394.375 | AP5: =IFERROR(ROUNDUP(O5/(1-CONFIGURACION!$B$6),0),0) -> 1992 | AQ5: =IFERROR(ROUNDUP(O5/(1-CONFIGURACION!$B$7),0),0) -> 3099 | AR5: =IFERROR(ROUNDUP(O5/(1-CONFIGURACION!$B$8),0),0) -> 4648 | AS5: 6500 | AT5: =IF(S5>0,(S5-O5)/S5,0) -> 0.78548077
A6: PP-002 | B6: Topper premium iluminado | C6: Topper con estructura y luz LED | D6: pieza | E6: =IFERROR(SUMIF(RECETAS!$B:$B,B6,RECETAS!$H:$H),0) -> 0 | F6: 8 | G6: 8 | H6: 0 | I6: 10 | J6: =F6+G6+H6+I6 -> 26 | K6: =IFERROR(CONFIGURACION!$B$5,0) -> 4000 | L6: =IFERROR(J6*K6/60,0) -> 1733.3333 | M6: =IFERROR(CONFIGURACION!$B$9,0) -> 0.15 | N6: =IFERROR((E6+L6)*M6,0) -> 260 | O6: =IFERROR(E6+L6+N6,0) -> 1993.3333 | P6: =IFERROR(ROUNDUP(O6/(1-CONFIGURACION!$B$6),0),0) -> 2848 | Q6: =IFERROR(ROUNDUP(O6/(1-CONFIGURACION!$B$7),0),0) -> 4430 | R6: =IFERROR(ROUNDUP(O6/(1-CONFIGURACION!$B$8),0),0) -> 6645 | S6: 22500 | T6: =IF(S6>0,(S6-O6)/S6,0) -> 0.91140741 | U6: =IF(S6=0,"SIN PRECIO",IF(T6<CONFIGURACION!$B$6,"BAJO COSTO",IF(T6<CONFIGURACION!$B$7,"REVISAR","OK"))) -> OK | AO6: =IFERROR(E6+L6+N6,0) -> 1993.3333 | AP6: =IFERROR(ROUNDUP(O6/(1-CONFIGURACION!$B$6),0),0) -> 2848 | AQ6: =IFERROR(ROUNDUP(O6/(1-CONFIGURACION!$B$7),0),0) -> 4430 | AR6: =IFERROR(ROUNDUP(O6/(1-CONFIGURACION!$B$8),0),0) -> 6645 | AS6: 22500 | AT6: =IF(S6>0,(S6-O6)/S6,0) -> 0.91140741
A7: PP-003 | B7: Tarjetas presentacion | C7: Set de 100 tarjetas impresas | D7: set 100u | E7: =IFERROR(SUMIF(RECETAS!$B:$B,B7,RECETAS!$H:$H),0) -> 717.5 | F7: 10 | G7: 10 | H7: 5 | I7: 2 | J7: =F7+G7+H7+I7 -> 27 | K7: =IFERROR(CONFIGURACION!$B$5,0) -> 4000 | L7: =IFERROR(J7*K7/60,0) -> 1800 | M7: =IFERROR(CONFIGURACION!$B$9,0) -> 0.15 | N7: =IFERROR((E7+L7)*M7,0) -> 377.625 | O7: =IFERROR(E7+L7+N7,0) -> 2895.125 | P7: =IFERROR(ROUNDUP(O7/(1-CONFIGURACION!$B$6),0),0) -> 4136 | Q7: =IFERROR(ROUNDUP(O7/(1-CONFIGURACION!$B$7),0),0) -> 6434 | R7: =IFERROR(ROUNDUP(O7/(1-CONFIGURACION!$B$8),0),0) -> 9651 | S7: 12500 | T7: =IF(S7>0,(S7-O7)/S7,0) -> 0.76839 | U7: =IF(S7=0,"SIN PRECIO",IF(T7<CONFIGURACION!$B$6,"BAJO COSTO",IF(T7<CONFIGURACION!$B$7,"REVISAR","OK"))) -> OK | AO7: =IFERROR(E7+L7+N7,0) -> 2895.125 | AP7: =IFERROR(ROUNDUP(O7/(1-CONFIGURACION!$B$6),0),0) -> 4136 | AQ7: =IFERROR(ROUNDUP(O7/(1-CONFIGURACION!$B$7),0),0) -> 6434 | AR7: =IFERROR(ROUNDUP(O7/(1-CONFIGURACION!$B$8),0),0) -> 9651 | AS7: 12500 | AT7: =IF(S7>0,(S7-O7)/S7,0) -> 0.76839
A8: PP-004 | B8: Flyer volante | C8: Impresion digital por unidad | D8: pieza | E8: =IFERROR(SUMIF(RECETAS!$B:$B,B8,RECETAS!$H:$H),0) -> 84 | F8: 3 | G8: 3 | H8: 0 | I8: 0 | J8: =F8+G8+H8+I8 -> 6 | K8: =IFERROR(CONFIGURACION!$B$5,0) -> 4000 | L8: =IFERROR(J8*K8/60,0) -> 400 | M8: =IFERROR(CONFIGURACION!$B$9,0) -> 0.15 | N8: =IFERROR((E8+L8)*M8,0) -> 72.6 | O8: =IFERROR(E8+L8+N8,0) -> 556.6 | P8: =IFERROR(ROUNDUP(O8/(1-CONFIGURACION!$B$6),0),0) -> 796 | Q8: =IFERROR(ROUNDUP(O8/(1-CONFIGURACION!$B$7),0),0) -> 1237 | R8: =IFERROR(ROUNDUP(O8/(1-CONFIGURACION!$B$8),0),0) -> 1856 | S8: 350 | T8: =IF(S8>0,(S8-O8)/S8,0) -> -0.59028571 | U8: =IF(S8=0,"SIN PRECIO",IF(T8<CONFIGURACION!$B$6,"BAJO COSTO",IF(T8<CONFIGURACION!$B$7,"REVISAR","OK"))) -> BAJO COSTO | AO8: =IFERROR(E8+L8+N8,0) -> 556.6 | AP8: =IFERROR(ROUNDUP(O8/(1-CONFIGURACION!$B$6),0),0) -> 796 | AQ8: =IFERROR(ROUNDUP(O8/(1-CONFIGURACION!$B$7),0),0) -> 1237 | AR8: =IFERROR(ROUNDUP(O8/(1-CONFIGURACION!$B$8),0),0) -> 1856 | AS8: 350 | AT8: =IF(S8>0,(S8-O8)/S8,0) -> -0.59028571
A9: PP-005 | B9: Etiqueta adhesiva | C9: Set 20 unidades personalizadas | D9: set 20u | E9: =IFERROR(SUMIF(RECETAS!$B:$B,B9,RECETAS!$H:$H),0) -> 386.25 | F9: 5 | G9: 5 | H9: 5 | I9: 0 | J9: =F9+G9+H9+I9 -> 15 | K9: =IFERROR(CONFIGURACION!$B$5,0) -> 4000 | L9: =IFERROR(J9*K9/60,0) -> 1000 | M9: =IFERROR(CONFIGURACION!$B$9,0) -> 0.15 | N9: =IFERROR((E9+L9)*M9,0) -> 207.9375 | O9: =IFERROR(E9+L9+N9,0) -> 1594.1875 | P9: =IFERROR(ROUNDUP(O9/(1-CONFIGURACION!$B$6),0),0) -> 2278 | Q9: =IFERROR(ROUNDUP(O9/(1-CONFIGURACION!$B$7),0),0) -> 3543 | R9: =IFERROR(ROUNDUP(O9/(1-CONFIGURACION!$B$8),0),0) -> 5314 | S9: 5500 | T9: =IF(S9>0,(S9-O9)/S9,0) -> 0.71014773 | U9: =IF(S9=0,"SIN PRECIO",IF(T9<CONFIGURACION!$B$6,"BAJO COSTO",IF(T9<CONFIGURACION!$B$7,"REVISAR","OK"))) -> OK | AO9: =IFERROR(E9+L9+N9,0) -> 1594.1875 | AP9: =IFERROR(ROUNDUP(O9/(1-CONFIGURACION!$B$6),0),0) -> 2278 | AQ9: =IFERROR(ROUNDUP(O9/(1-CONFIGURACION!$B$7),0),0) -> 3543 | AR9: =IFERROR(ROUNDUP(O9/(1-CONFIGURACION!$B$8),0),0) -> 5314 | AS9: 5500 | AT9: =IF(S9>0,(S9-O9)/S9,0) -> 0.71014773
A10: PP-006 | B10: Sticker personalizado | C10: Set 20 stickers con diseno | D10: set 20u | E10: =IFERROR(SUMIF(RECETAS!$B:$B,B10,RECETAS!$H:$H),0) -> 435 | F10: 5 | G10: 5 | H10: 5 | I10: 0 | J10: =F10+G10+H10+I10 -> 15 | K10: =IFERROR(CONFIGURACION!$B$5,0) -> 4000 | L10: =IFERROR(J10*K10/60,0) -> 1000 | M10: =IFERROR(CONFIGURACION!$B$9,0) -> 0.15 | N10: =IFERROR((E10+L10)*M10,0) -> 215.25 | O10: =IFERROR(E10+L10+N10,0) -> 1650.25 | P10: =IFERROR(ROUNDUP(O10/(1-CONFIGURACION!$B$6),0),0) -> 2358 | Q10: =IFERROR(ROUNDUP(O10/(1-CONFIGURACION!$B$7),0),0) -> 3668 | R10: =IFERROR(ROUNDUP(O10/(1-CONFIGURACION!$B$8),0),0) -> 5501 | S10: 4000 | T10: =IF(S10>0,(S10-O10)/S10,0) -> 0.5874375 | U10: =IF(S10=0,"SIN PRECIO",IF(T10<CONFIGURACION!$B$6,"BAJO COSTO",IF(T10<CONFIGURACION!$B$7,"REVISAR","OK"))) -> OK | AO10: =IFERROR(E10+L10+N10,0) -> 1650.25 | AP10: =IFERROR(ROUNDUP(O10/(1-CONFIGURACION!$B$6),0),0) -> 2358 | AQ10: =IFERROR(ROUNDUP(O10/(1-CONFIGURACION!$B$7),0),0) -> 3668 | AR10: =IFERROR(ROUNDUP(O10/(1-CONFIGURACION!$B$8),0),0) -> 5501 | AS10: 4000 | AT10: =IF(S10>0,(S10-O10)/S10,0) -> 0.5874375
A11: PP-007 | B11: Vinil personalizado | C11: Vinil cortado con diseno | D11: pieza | E11: =IFERROR(SUMIF(RECETAS!$B:$B,B11,RECETAS!$H:$H),0) -> 426.25 | F11: 10 | G11: 5 | H11: 10 | I11: 5 | J11: =F11+G11+H11+I11 -> 30 | K11: =IFERROR(CONFIGURACION!$B$5,0) -> 4000 | L11: =IFERROR(J11*K11/60,0) -> 2000 | M11: =IFERROR(CONFIGURACION!$B$9,0) -> 0.15 | N11: =IFERROR((E11+L11)*M11,0) -> 363.9375 | O11: =IFERROR(E11+L11+N11,0) -> 2790.1875 | P11: =IFERROR(ROUNDUP(O11/(1-CONFIGURACION!$B$6),0),0) -> 3986 | Q11: =IFERROR(ROUNDUP(O11/(1-CONFIGURACION!$B$7),0),0) -> 6201 | R11: =IFERROR(ROUNDUP(O11/(1-CONFIGURACION!$B$8),0),0) -> 9301 | S11: 9500 | T11: =IF(S11>0,(S11-O11)/S11,0) -> 0.70629605 | U11: =IF(S11=0,"SIN PRECIO",IF(T11<CONFIGURACION!$B$6,"BAJO COSTO",IF(T11<CONFIGURACION!$B$7,"REVISAR","OK"))) -> OK | AO11: =IFERROR(E11+L11+N11,0) -> 2790.1875 | AP11: =IFERROR(ROUNDUP(O11/(1-CONFIGURACION!$B$6),0),0) -> 3986 | AQ11: =IFERROR(ROUNDUP(O11/(1-CONFIGURACION!$B$7),0),0) -> 6201 | AR11: =IFERROR(ROUNDUP(O11/(1-CONFIGURACION!$B$8),0),0) -> 9301 | AS11: 9500 | AT11: =IF(S11>0,(S11-O11)/S11,0) -> 0.70629605
A12: PP-008 | B12: Polera sublimada | C12: Polera con diseno sublimado | D12: pieza | E12: =IFERROR(SUMIF(RECETAS!$B:$B,B12,RECETAS!$H:$H),0) -> 3635 | F12: 10 | G12: 8 | H12: 5 | I12: 7 | J12: =F12+G12+H12+I12 -> 30 | K12: =IFERROR(CONFIGURACION!$B$5,0) -> 4000 | L12: =IFERROR(J12*K12/60,0) -> 2000 | M12: =IFERROR(CONFIGURACION!$B$9,0) -> 0.15 | N12: =IFERROR((E12+L12)*M12,0) -> 845.25 | O12: =IFERROR(E12+L12+N12,0) -> 6480.25 | P12: =IFERROR(ROUNDUP(O12/(1-CONFIGURACION!$B$6),0),0) -> 9258 | Q12: =IFERROR(ROUNDUP(O12/(1-CONFIGURACION!$B$7),0),0) -> 14401 | R12: =IFERROR(ROUNDUP(O12/(1-CONFIGURACION!$B$8),0),0) -> 21601 | S12: 8500 | T12: =IF(S12>0,(S12-O12)/S12,0) -> 0.23761765 | U12: =IF(S12=0,"SIN PRECIO",IF(T12<CONFIGURACION!$B$6,"BAJO COSTO",IF(T12<CONFIGURACION!$B$7,"REVISAR","OK"))) -> BAJO COSTO | AO12: =IFERROR(E12+L12+N12,0) -> 6480.25 | AP12: =IFERROR(ROUNDUP(O12/(1-CONFIGURACION!$B$6),0),0) -> 9258 | AQ12: =IFERROR(ROUNDUP(O12/(1-CONFIGURACION!$B$7),0),0) -> 14401 | AR12: =IFERROR(ROUNDUP(O12/(1-CONFIGURACION!$B$8),0),0) -> 21601 | AS12: 8500 | AT12: =IF(S12>0,(S12-O12)/S12,0) -> 0.23761765
A13: PP-009 | B13: Pendon publicitario | C13: Pendon 60x160cm impreso | D13: pieza | E13: =IFERROR(SUMIF(RECETAS!$B:$B,B13,RECETAS!$H:$H),0) -> 7767.5 | F13: 15 | G13: 15 | H13: 0 | I13: 15 | J13: =F13+G13+H13+I13 -> 45 | K13: =IFERROR(CONFIGURACION!$B$5,0) -> 4000 | L13: =IFERROR(J13*K13/60,0) -> 3000 | M13: =IFERROR(CONFIGURACION!$B$9,0) -> 0.15 | N13: =IFERROR((E13+L13)*M13,0) -> 1615.125 | O13: =IFERROR(E13+L13+N13,0) -> 12382.625 | P13: =IFERROR(ROUNDUP(O13/(1-CONFIGURACION!$B$6),0),0) -> 17690 | Q13: =IFERROR(ROUNDUP(O13/(1-CONFIGURACION!$B$7),0),0) -> 27517 | R13: =IFERROR(ROUNDUP(O13/(1-CONFIGURACION!$B$8),0),0) -> 41276 | S13: 18000 | T13: =IF(S13>0,(S13-O13)/S13,0) -> 0.31207639 | U13: =IF(S13=0,"SIN PRECIO",IF(T13<CONFIGURACION!$B$6,"BAJO COSTO",IF(T13<CONFIGURACION!$B$7,"REVISAR","OK"))) -> REVISAR | AO13: =IFERROR(E13+L13+N13,0) -> 12382.625 | AP13: =IFERROR(ROUNDUP(O13/(1-CONFIGURACION!$B$6),0),0) -> 17690 | AQ13: =IFERROR(ROUNDUP(O13/(1-CONFIGURACION!$B$7),0),0) -> 27517 | AR13: =IFERROR(ROUNDUP(O13/(1-CONFIGURACION!$B$8),0),0) -> 41276 | AS13: 18000 | AT13: =IF(S13>0,(S13-O13)/S13,0) -> 0.31207639
A14: PP-010 | B14: Caja personalizada | C14: Caja troquelada con diseno | D14: pieza | E14: =IFERROR(SUMIF(RECETAS!$B:$B,B14,RECETAS!$H:$H),0) -> 325 | F14: 15 | G14: 5 | H14: 15 | I14: 10 | J14: =F14+G14+H14+I14 -> 45 | K14: =IFERROR(CONFIGURACION!$B$5,0) -> 4000 | L14: =IFERROR(J14*K14/60,0) -> 3000 | M14: =IFERROR(CONFIGURACION!$B$9,0) -> 0.15 | N14: =IFERROR((E14+L14)*M14,0) -> 498.75 | O14: =IFERROR(E14+L14+N14,0) -> 3823.75 | P14: =IFERROR(ROUNDUP(O14/(1-CONFIGURACION!$B$6),0),0) -> 5463 | Q14: =IFERROR(ROUNDUP(O14/(1-CONFIGURACION!$B$7),0),0) -> 8498 | R14: =IFERROR(ROUNDUP(O14/(1-CONFIGURACION!$B$8),0),0) -> 12746 | S14: 7500 | T14: =IF(S14>0,(S14-O14)/S14,0) -> 0.49016667 | U14: =IF(S14=0,"SIN PRECIO",IF(T14<CONFIGURACION!$B$6,"BAJO COSTO",IF(T14<CONFIGURACION!$B$7,"REVISAR","OK"))) -> REVISAR | AO14: =IFERROR(E14+L14+N14,0) -> 3823.75 | AP14: =IFERROR(ROUNDUP(O14/(1-CONFIGURACION!$B$6),0),0) -> 5463 | AQ14: =IFERROR(ROUNDUP(O14/(1-CONFIGURACION!$B$7),0),0) -> 8498 | AR14: =IFERROR(ROUNDUP(O14/(1-CONFIGURACION!$B$8),0),0) -> 12746 | AS14: 7500 | AT14: =IF(S14>0,(S14-O14)/S14,0) -> 0.49016667

Sheet VENTAS
A1: PAINT PRINT -- REGISTRO DE VENTAS Y PEDIDOS
A2: Ingresa: Fecha, Cliente, Producto, Cantidad, Precio cobrado, Minutos trabajados. El sistema calcula lo demas.
A3: Si el MARGEN es negativo o rojo -- el precio cobrado es menor que tu costo real.
A4: N PEDIDO | B4: FECHA | C4: CLIENTE | D4: PRODUCTO | E4: CANT. | F4: PRECIO COBRADO $ | G4: TOTAL VENTA $ | H4: COSTO UNIT $ | I4: COSTO TOTAL $ | J4: UTILIDAD $ | K4: MARGEN % | L4: MIN TRAB. | M4: GANANCIA/HORA $ | N4: CANAL | AO4: ESTADO | AP4: OBSERVACIONES
A5: P-001 | B5: 46195 | C5: Cliente Ejemplo | D5: Topper personalizado | E5: 10 | F5: 6500 | G5: =IFERROR(E5*F5,0) -> 65000 | H5: =IFERROR(VLOOKUP(D5,PRODUCTOS!$B:$O,14,0),0) -> 1394.375 | I5: =IFERROR(E5*H5,0) -> 13943.75 | J5: =IFERROR(G5-I5,0) -> 51056.25 | K5: =IF(G5>0,J5/G5,0) -> 0.78548077 | L5: 75 | M5: =IF(L5>0,J5/(L5/60),0) -> 40845 | N5: Instagram | AO5: Pagado | AP5: Pedido de ejemplo -- reemplazar con pedidos reales
A6: P-002 | C6: -- Agrega tu proximo pedido aqui -- | G6: =IFERROR(E6*F6,0) -> 0 | H6: =IFERROR(VLOOKUP(D6,PRODUCTOS!$B:$O,14,0),0) -> 0 | I6: =IFERROR(E6*H6,0) -> 0 | J6: =IFERROR(G6-I6,0) -> 0 | K6: =IF(G6>0,J6/G6,0) -> 0 | M6: =IF(L6>0,J6/(L6/60),0) -> 0
A105: TOTALES DEL MES | G105: =SUM(G5:G104) -> 65000 | I105: =SUM(I5:I104) -> 13943.75 | J105: =SUM(J5:J104) -> 51056.25 | K105: =IFERROR(J105/G105,0) -> 0.78548077

Sheet MOVIMIENTOS
A1: PAINT PRINT -- MOVIMIENTOS DE INVENTARIO
A2: Registra cada entrada de material (compra) y cada salida (produccion, merma). El stock en MATERIALES se actualiza automaticamente.
A3: TIPO: ENTRADA=compra | SALIDA=usado en produccion | MERMA=desperdicio | AJUSTE=correccion manual
A4: FECHA | B4: TIPO | C4: ID MATERIAL | D4: MATERIAL | E4: CANTIDAD | F4: UNIDAD | G4: COSTO/UNID $ | H4: VALOR MOV $ | I4: N PEDIDO REF | J4: NOTA
A5: 46195 | B5: ENTRADA | C5: MP-001 | D5: =IFERROR(VLOOKUP(C5,MATERIALES!$A:$B,2,0),"") -> Papel fotografico 260g | E5: 100 | F5: =IFERROR(VLOOKUP(C5,MATERIALES!$A:$F,6,0),"") -> hoja | G5: =IFERROR(VLOOKUP(C5,MATERIALES!$A:$I,9,0),0) -> 250 | H5: =IFERROR(E5*G5,0) -> 25000 | I5: STOCK INICIAL | J5: Stock inicial al comenzar el sistema
A6: 46195 | B6: ENTRADA | C6: MP-002 | D6: =IFERROR(VLOOKUP(C6,MATERIALES!$A:$B,2,0),"") -> Papel fotografico 180g | E6: 100 | F6: =IFERROR(VLOOKUP(C6,MATERIALES!$A:$F,6,0),"") -> hoja | G6: =IFERROR(VLOOKUP(C6,MATERIALES!$A:$I,9,0),0) -> 70 | H6: =IFERROR(E6*G6,0) -> 7000 | I6: STOCK INICIAL | J6: Stock inicial al comenzar el sistema
A7: 46195 | B7: ENTRADA | C7: MP-003 | D7: =IFERROR(VLOOKUP(C7,MATERIALES!$A:$B,2,0),"") -> Vinil imprimible (pack 20u) | E7: 40 | F7: =IFERROR(VLOOKUP(C7,MATERIALES!$A:$F,6,0),"") -> unidad | G7: =IFERROR(VLOOKUP(C7,MATERIALES!$A:$I,9,0),0) -> 400 | H7: =IFERROR(E7*G7,0) -> 16000 | I7: STOCK INICIAL | J7: Stock inicial al comenzar el sistema
A8: 46195 | B8: ENTRADA | C8: MP-004 | D8: =IFERROR(VLOOKUP(C8,MATERIALES!$A:$B,2,0),"") -> Vinil textil por metro | E8: 500 | F8: =IFERROR(VLOOKUP(C8,MATERIALES!$A:$F,6,0),"") -> centimetro | G8: =IFERROR(VLOOKUP(C8,MATERIALES!$A:$I,9,0),0) -> 60 | H8: =IFERROR(E8*G8,0) -> 30000 | I8: STOCK INICIAL | J8: Stock inicial al comenzar el sistema
A9: 46195 | B9: ENTRADA | C9: MP-005 | D9: =IFERROR(VLOOKUP(C9,MATERIALES!$A:$B,2,0),"") -> Papel adhesivo | E9: 50 | F9: =IFERROR(VLOOKUP(C9,MATERIALES!$A:$F,6,0),"") -> hoja | G9: =IFERROR(VLOOKUP(C9,MATERIALES!$A:$I,9,0),0) -> 180 | H9: =IFERROR(E9*G9,0) -> 9000 | I9: STOCK INICIAL | J9: Stock inicial al comenzar el sistema
A10: 46195 | B10: ENTRADA | C10: MP-006 | D10: =IFERROR(VLOOKUP(C10,MATERIALES!$A:$B,2,0),"") -> Cartulina opalina | E10: 40 | F10: =IFERROR(VLOOKUP(C10,MATERIALES!$A:$F,6,0),"") -> hoja | G10: =IFERROR(VLOOKUP(C10,MATERIALES!$A:$I,9,0),0) -> 150 | H10: =IFERROR(E10*G10,0) -> 6000 | I10: STOCK INICIAL | J10: Stock inicial al comenzar el sistema
A11: 46195 | B11: ENTRADA | C11: MP-007 | D11: =IFERROR(VLOOKUP(C11,MATERIALES!$A:$B,2,0),"") -> Pegamento | E11: 3 | F11: =IFERROR(VLOOKUP(C11,MATERIALES!$A:$F,6,0),"") -> uso | G11: =IFERROR(VLOOKUP(C11,MATERIALES!$A:$I,9,0),0) -> 50 | H11: =IFERROR(E11*G11,0) -> 150 | I11: STOCK INICIAL | J11: Stock inicial al comenzar el sistema
A12: 46195 | B12: ENTRADA | C12: MP-008 | D12: =IFERROR(VLOOKUP(C12,MATERIALES!$A:$B,2,0),"") -> Palitos para toppers | E12: 200 | F12: =IFERROR(VLOOKUP(C12,MATERIALES!$A:$F,6,0),"") -> unidad | G12: =IFERROR(VLOOKUP(C12,MATERIALES!$A:$I,9,0),0) -> 15 | H12: =IFERROR(E12*G12,0) -> 3000 | I12: STOCK INICIAL | J12: Stock inicial al comenzar el sistema
A13: 46195 | B13: ENTRADA | C13: MP-009 | D13: =IFERROR(VLOOKUP(C13,MATERIALES!$A:$B,2,0),"") -> Tinta Epson (set completo) | E13: 400 | F13: =IFERROR(VLOOKUP(C13,MATERIALES!$A:$F,6,0),"") -> uso | G13: =IFERROR(VLOOKUP(C13,MATERIALES!$A:$I,9,0),0) -> 175 | H13: =IFERROR(E13*G13,0) -> 70000 | I13: STOCK INICIAL | J13: Stock inicial al comenzar el sistema
A14: 46195 | B14: ENTRADA | C14: MP-010 | D14: =IFERROR(VLOOKUP(C14,MATERIALES!$A:$B,2,0),"") -> Lona para pendones | E14: 50000 | F14: =IFERROR(VLOOKUP(C14,MATERIALES!$A:$F,6,0),"") -> cm2 | G14: =IFERROR(VLOOKUP(C14,MATERIALES!$A:$I,9,0),0) -> 0.8 | H14: =IFERROR(E14*G14,0) -> 40000 | I14: STOCK INICIAL | J14: Stock inicial al comenzar el sistema
